EBG/__init__.py
EBG/__main__.py
EBG/Features/__init__.py
EBG/Features/feature_computer.py
EBG/Features/feature_extractor.py
EBG/Features/parsimony_mutation_counter.py
EBG/Models/__init__.py
EBG/Models/class_70.pkl
EBG/Models/class_75.pkl
EBG/Models/class_80.pkl
EBG/Models/class_85.pkl
EBG/Models/get_model.py
EBG/Models/low_model_10.pkl
EBG/Models/low_model_5.pkl
EBG/Models/median_model.pkl
EBG/Prediction/__init__.py
EBG/Prediction/predictor.py
EBG/utils/__init__.py
EBG/utils/utils.py
ebg-1.0.dist-info/METADATA
ebg-1.0.dist-info/WHEEL
ebg-1.0.dist-info/entry_points.txt
ebg-1.0.dist-info/top_level.txt
ebg-1.0.dist-info/RECORD
