Metadata-Version: 2.1
Name: ebg
Version: 1.0
Requires-Dist: pandas
Requires-Dist: numpy
Requires-Dist: ete3
Requires-Dist: biopython
Requires-Dist: networkx
Requires-Dist: scipy
Requires-Dist: lightgbm
